rinoh_typeface_texgyreschola/GUST-FONT-LICENSE.txt
rinoh_typeface_texgyreschola/README-TeX-Gyre-Schola.txt
rinoh_typeface_texgyreschola/__init__.py
rinoh_typeface_texgyreschola/texgyreschola-bold.otf
rinoh_typeface_texgyreschola/texgyreschola-bolditalic.otf
rinoh_typeface_texgyreschola/texgyreschola-italic.otf
rinoh_typeface_texgyreschola/texgyreschola-regular.otf
rinoh_typeface_texgyreschola-0.1.1.dist-info/DESCRIPTION.rst
rinoh_typeface_texgyreschola-0.1.1.dist-info/METADATA
rinoh_typeface_texgyreschola-0.1.1.dist-info/RECORD
rinoh_typeface_texgyreschola-0.1.1.dist-info/WHEEL
rinoh_typeface_texgyreschola-0.1.1.dist-info/entry_points.txt
rinoh_typeface_texgyreschola-0.1.1.dist-info/metadata.json
rinoh_typeface_texgyreschola-0.1.1.dist-info/top_level.txt
